{
  "version": "5",
  "dialect": "pg",
  "entries": [
    {
      "idx": 0,
      "version": "5",
      "when": 1710494413406,
      "tag": "0000_watery_monster_badoon",
      "breakpoints": true
    },
    {
      "idx": 1,
      "version": "5",
      "when": 1710494418096,
      "tag": "0001_faithful_mysterio",
      "breakpoints": true
    },
    {
      "idx": 2,
      "version": "5",
      "when": 1710784048999,
      "tag": "0002_tricky_sinister_six",
      "breakpoints": true
    },
    {
      "idx": 3,
      "version": "5",
      "when": 1710784077180,
      "tag": "0003_fixed_black_knight",
      "breakpoints": true
    },
    {
      "idx": 4,
      "version": "5",
      "when": 1710784089316,
      "tag": "0004_lovely_roxanne_simpson",
      "breakpoints": true
    },
    {
      "idx": 5,
      "version": "7",
      "when": 1733332779497,
      "tag": "0005_funny_maggott",
      "breakpoints": true
    },
    {
      "idx": 6,
      "version": "7",
      "when": 1733333083392,
      "tag": "0006_minor_the_call",
      "breakpoints": true
    },
    {
      "idx": 7,
      "version": "7",
      "when": 1746435531311,
      "tag": "0007_clean_wolf_cub",
      "breakpoints": true
    }
  ]
}
